cli.py
config.py
play.py
services.py
volume.py
spty-0.1.4.dist-info/LICENSE
spty-0.1.4.dist-info/METADATA
spty-0.1.4.dist-info/WHEEL
spty-0.1.4.dist-info/entry_points.txt
spty-0.1.4.dist-info/top_level.txt
spty-0.1.4.dist-info/RECORD
